gitprivacy/__init__.py
gitprivacy/gitprivacy.py
gitprivacy/utils.py
gitprivacy/cli/__init__.py
gitprivacy/cli/email.py
gitprivacy/cli/keys.py
gitprivacy/cli/pushcheck.py
gitprivacy/cli/utils.py
gitprivacy/crypto/__init__.py
gitprivacy/crypto/passwordsecretbox.py
gitprivacy/crypto/secretbox.py
gitprivacy/dateredacter/__init__.py
gitprivacy/dateredacter/reduce.py
gitprivacy/encoder/__init__.py
gitprivacy/encoder/msgembed.py
gitprivacy/resources/__init__.py
gitprivacy/resources/__pycache__/__init__.cpython-310.pyc
gitprivacy/resources/__pycache__/__init__.cpython-37.pyc
gitprivacy/resources/__pycache__/__init__.cpython-38.pyc
gitprivacy/resources/__pycache__/__init__.cpython-39.pyc
gitprivacy/resources/hooks/__init__.py
gitprivacy/resources/hooks/post-commit
gitprivacy/resources/hooks/post-rewrite
gitprivacy/resources/hooks/pre-commit
gitprivacy/resources/hooks/pre-push
gitprivacy/resources/hooks/__pycache__/__init__.cpython-310.pyc
gitprivacy/resources/hooks/__pycache__/__init__.cpython-37.pyc
gitprivacy/resources/hooks/__pycache__/__init__.cpython-38.pyc
gitprivacy/resources/hooks/__pycache__/__init__.cpython-39.pyc
gitprivacy/rewriter/__init__.py
gitprivacy/rewriter/amendrewriter.py
gitprivacy/rewriter/filterrewriter.py
gitprivacy-2.3.0.dist-info/LICENSE
gitprivacy-2.3.0.dist-info/METADATA
gitprivacy-2.3.0.dist-info/WHEEL
gitprivacy-2.3.0.dist-info/entry_points.txt
gitprivacy-2.3.0.dist-info/top_level.txt
gitprivacy-2.3.0.dist-info/RECORD
