Metadata-Version: 2.1
Name: gitprivacy
Version: 2.3.0
Summary: Git wrapper redacting author and committer dates.
Home-page: https://github.com/EMPRI-DEVOPS/git-privacy
Maintainer: Christian Burkert
Maintainer-email: gitprivacy@cburkert.de
License: BSD
Keywords: git,privacy,timestamps
Platform: UNKNOWN
Classifier: Topic :: Software Development :: Version Control :: Git
Classifier: Programming Language :: Python :: 3
Classifier: Programming Language :: Python :: 3 :: Only
Classifier: Programming Language :: Python :: 3.6
Classifier: Programming Language :: Python :: 3.7
Classifier: Programming Language :: Python :: 3.8
Classifier: Programming Language :: Python :: 3.9
Classifier: Programming Language :: Python :: 3.10
Classifier: License :: OSI Approved :: BSD License
Classifier: Operating System :: OS Independent
Requires-Python: >=3.6
License-File: LICENSE
Requires-Dist: click (>=7)
Requires-Dist: gitpython
Requires-Dist: git-filter-repo (>=2.27)
Requires-Dist: pynacl
